odoo9_addon_base_fontawesome-9.0.4.7.0-py2.7-nspkg.pth
odoo9_addon_base_fontawesome-9.0.4.7.0.dist-info/DESCRIPTION.rst
odoo9_addon_base_fontawesome-9.0.4.7.0.dist-info/METADATA
odoo9_addon_base_fontawesome-9.0.4.7.0.dist-info/RECORD
odoo9_addon_base_fontawesome-9.0.4.7.0.dist-info/WHEEL
odoo9_addon_base_fontawesome-9.0.4.7.0.dist-info/metadata.json
odoo9_addon_base_fontawesome-9.0.4.7.0.dist-info/namespace_packages.txt
odoo9_addon_base_fontawesome-9.0.4.7.0.dist-info/top_level.txt
odoo_addons/base_fontawesome/README.rst
odoo_addons/base_fontawesome/__init__.py
odoo_addons/base_fontawesome/__openerp__.py
odoo_addons/base_fontawesome/static/description/icon.png
odoo_addons/base_fontawesome/static/lib/fontawesome-4.7.0/css/font-awesome.css
odoo_addons/base_fontawesome/static/lib/fontawesome-4.7.0/fonts/FontAwesome.otf
odoo_addons/base_fontawesome/static/lib/fontawesome-4.7.0/fonts/fontawesome-webfont.eot
odoo_addons/base_fontawesome/static/lib/fontawesome-4.7.0/fonts/fontawesome-webfont.svg
odoo_addons/base_fontawesome/static/lib/fontawesome-4.7.0/fonts/fontawesome-webfont.ttf
odoo_addons/base_fontawesome/static/lib/fontawesome-4.7.0/fonts/fontawesome-webfont.woff
odoo_addons/base_fontawesome/static/lib/fontawesome-4.7.0/fonts/fontawesome-webfont.woff2
odoo_addons/base_fontawesome/templates/assets.xml
