Metadata-Version: 2.0
Name: odoo9-addon-base-fontawesome
Version: 9.0.4.7.0
Summary: Up to date Fontawesome resources.
Home-page: UNKNOWN
Author: Camptocamp,Odoo Community Association (OCA)
Author-email: support@odoo-community.org
License: LGPL-3
Platform: UNKNOWN
Classifier: Programming Language :: Python :: 2.7
Classifier: Framework :: Odoo
Classifier: License :: OSI Approved :: GNU Lesser General Public License v3 (LGPLv3)
Requires-Dist: odoo (<9.1a,>=9.0a)
